{"cameraMode":{"drawMode":0,"name":"Shaded","section":"Shading Mode"},"sceneLighting":false,"audioPlay":false,"sceneViewState":{"m_AlwaysRefresh":false,"showFog":true,"showSkybox":false,"showFlares":true,"showImageEffects":true,"showParticleSystems":true,"showVisualEffectGraphs":true,"m_FxEnabled":true},"in2DMode":false,"pivot":{"x":2.5373244285583498,"y":0.5573038458824158,"z":3.074042797088623},"rotation":{"x":-0.613831639289856,"y":-0.09249920397996903,"z":0.07316622883081436,"w":-0.780759871006012},"size":8.447092056274414,"orthographic":false}